unsloth_mlx/__init__.py
unsloth_mlx/chat_templates.py
unsloth_mlx/losses.py
unsloth_mlx/model.py
unsloth_mlx/rl_trainers.py
unsloth_mlx/sft_trainer.py
unsloth_mlx/trainer.py
unsloth_mlx/vlm.py
unsloth_mlx-0.3.4.dist-info/licenses/LICENSE
unsloth_mlx-0.3.4.dist-info/METADATA
unsloth_mlx-0.3.4.dist-info/WHEEL
unsloth_mlx-0.3.4.dist-info/top_level.txt
unsloth_mlx-0.3.4.dist-info/RECORD
