Metadata-Version: 2.4
Name: unsloth-mlx
Version: 0.3.4
Summary: MLX-powered LLM fine-tuning for Apple Silicon - A drop-in replacement for Unsloth
Author: Unsloth-MLX Contributors
License: Apache-2.0
Project-URL: Homepage, https://github.com/ARahim3/unsloth-mlx
Project-URL: Documentation, https://github.com/ARahim3/unsloth-mlx#readme
Project-URL: Repository, https://github.com/ARahim3/unsloth-mlx
Project-URL: Issues, https://github.com/ARahim3/unsloth-mlx/issues
Keywords: llm,fine-tuning,mlx,apple-silicon,lora,unsloth,mac
Classifier: Development Status :: 3 - Alpha
Classifier: Intended Audience :: Developers
Classifier: Intended Audience :: Science/Research
Classifier: License :: OSI Approved :: Apache Software License
Classifier: Programming Language :: Python :: 3
Classifier: Programming Language :: Python :: 3.9
Classifier: Programming Language :: Python :: 3.10
Classifier: Programming Language :: Python :: 3.11
Classifier: Programming Language :: Python :: 3.12
Classifier: Topic :: Scientific/Engineering :: Artificial Intelligence
Requires-Python: >=3.9
License-File: LICENSE
Requires-Dist: mlx>=0.20.0
Requires-Dist: mlx-lm>=0.18.0
Requires-Dist: transformers>=4.36.0
Requires-Dist: tokenizers>=0.15.0
Requires-Dist: datasets>=2.14.0
Requires-Dist: huggingface-hub>=0.20.0
Requires-Dist: numpy>=1.23.0
Requires-Dist: tqdm>=4.65.0
Provides-Extra: dev
Requires-Dist: pytest>=7.4.0; extra == "dev"
Requires-Dist: pytest-cov>=4.1.0; extra == "dev"
Requires-Dist: black>=23.7.0; extra == "dev"
Requires-Dist: ruff>=0.0.284; extra == "dev"
Requires-Dist: ipython>=8.12.0; extra == "dev"
Provides-Extra: vlm
Requires-Dist: mlx-vlm>=0.1.0; extra == "vlm"
Provides-Extra: train
Requires-Dist: trl>=0.7.0; extra == "train"
Requires-Dist: peft>=0.7.0; extra == "train"
Requires-Dist: wandb>=0.15.0; extra == "train"
Provides-Extra: all
Requires-Dist: unsloth-mlx[dev,train,vlm]; extra == "all"
Dynamic: license-file
